Workbook

Sheet Start Here
B1: CI Knowledge Management: discovery and foundation
B2: Write down what continuous improvement (CI) already produces, where it lives, who uses it, and where reuse fails. This workbook feeds the design-and-foundation statement of work (SOW). It does not start a platform build.
B4: What problem this solves
B5: CI already runs lookbacks (plan vs actual), Integrated Backcasting and other backcasts (actual vs best possible), post-audits, recurring CI reports, and decision reviews. Those reviews produce files, emails, and know-how held by subject matter experts. The learning often stops there. The next person cannot find it, the planning model does not change, and the same issue comes back. This workbook captures a plain picture of that work so the CI knowledge-management (KM) framework is specified from evidence, not guesses.
B7: How the sheets connect
B8: R0 holds the two existing requirements packs: the Value Chain Optimization (VCO) KM Functional Requirements Document, and the AI-enabled KM requirements written through Integrated Backcasting. Coverage is who we have talked to. M1 lists every CI output (P-). M2 lists every system those outputs live in (S-). M3 says, for each P- item, who uses it and whether anything actually changes. M4 lists know-how that is only in people's heads (K-). M5 lists pains in the business's own words (PP-). M6 turns pains and assets into needs (N-) for the reconciled requirements list this SOW will produce. Each need points back to a PP-, P-, or K- ID. Glossary and Typical pains are reference only.
B10: Work in this order. Do not fill every sheet on day one. These steps are fill order, not implementation phases.
B11: Order | C11: Sheet | D11: What you capture | E11: Who sits in the room | F11: Effort
B12: 0 | C12: R0 Requirements | D12: The two existing requirements packs: aligned, unique, conflict, gap, or needs a COMPANY decision. | E12: Project lead plus Digital | F12: Living list
B13: 0 | C13: Coverage | D13: Sites and CI teams we have spoken to, so we know when a module is done. | E13: Project lead | F13: Living list
B14: 1 | C14: M1 Produced | D14: Every report, deck, spreadsheet, matrix, minutes, log, or decision email the CI work produces. | E14: People who produce the CI outputs | F14: 1-2 short sessions
B15: 1 | C15: M2 Systems | D15: The tools and folders where those items are made and stored, and whether a normal person can find them. | E15: Digital plus one user per system | F15: 1 session
B16: 2 | C16: M3 How used | D16: For each M1 item: who uses it, for what, and what happens next. Filed, nothing further is a useful answer. | E16: People who use the outputs | F16: 1-2 sessions
B17: 3 | C17: M4 People | D17: Judgment that is not written down, and the risk if that person leaves or rotates. | E17: CI managers and experienced CI staff | F17: Short interviews
B18: 3 | C18: M5 Pains | D18: Where it hurts today, in plain words, with a real example. | E18: Mixed CI group | F18: 1 session
B19: 4 | C19: M6 Needs | D19: What the CI KM framework must support, as outcomes not tools, each tied to a pain or asset. | E19: Sponsor plus module leads | F19: 1 session
B21: ID rules - use these prefixes and never invent a second scheme
B22: R-01 requirements (R0) | P-01 outputs (M1) | S-01 systems (M2) | K-01 people (M4) | PP-01 pains (M5) | N-01 needs (M6). Other sheets point at these IDs. Keep each ID unique. Example rows are already filled - replace or delete them.
B24: How to fill any sheet
B25: 1. Read the help row under the column titles. It says what belongs in that column, in plain words.
B26: 2. Look at the EXAMPLE rows. Copy that style. Then overwrite or delete them.
B27: 3. Where you see a dropdown, pick the closest option. Use Notes if nothing fits.
B28: 4. Do not wait for perfect. A rough row today is better than a precise row that never gets written.
B29: 5. Tick Coverage when a site or team is done for that module, so you know when to stop interviewing.
B31: Reference sheets: Glossary (every term) | Typical pains: optional examples of where knowledge work usually hurts. Used as optional tags on M5 and M6. Click a sheet name in the table above to jump there.
B33: Open Glossary | D33: Open Typical pains
B35: Prepared for the CI KM design-and-foundation SOW. This engagement does not implement a platform.

Sheet R0 Requirements
A1: R0 - Existing requirements (do not start from a blank page)
A2: COMPANY already has two requirements packs. Record each requirement here, then mark how it lines up. Discovery checks this list against the CI work we actually find.
A3: Start here, with the two packs in hand. IDs must be R-01, R-02… Other sheets may point at these IDs.
A4: Example row? | B4: Req ID | C4: Source pack | D4: Requirement (plain words) | E4: Alignment | F4: Unique to | G4: Conflict or gap | H4: COMPANY decision needed? | I4: Validated in discovery? | J4: Notes
A5: Yes = example. Change to No when it is a real line, or delete the row. | B5: R-01, R-02… Must be unique. Other sheets may point here. | C5: Which pack the line comes from. | D5: The requirement in one or two sentences, in plain words. | E5: How it lines up: aligned, unique, conflict, gap, or needs a COMPANY decision. | F5: If Unique, which pack it belongs to. | G5: What conflicts, or what is missing. | H5: Yes if COMPANY must decide before the line can be used. | I5: Whether discovery has checked this line against the CI work we find. | J5: Source reference, open questions, anything else.
A6: Yes | B6: R-01 | C6: Both | D6: CI knowledge must be findable by people who did not produce it | E6: Aligned | H6: No | I6: Not started | J6: EXAMPLE - replace with a real line from the two packs
A7: No | B7: R-02
A8: No | B8: R-03
A9: No | B9: R-04
A10: No | B10: R-05
A11: No | B11: R-06
A12: No | B12: R-07
A13: No | B13: R-08
A14: No | B14: R-09
A15: No | B15: R-10
A16: No | B16: R-11
A17: No | B17: R-12
A18: No | B18: R-13
... A45: No | B45: R-40

Sheet Coverage
A1: Coverage - who we have talked to
A2: Tick a module when that site or CI team is done. This is how you know the discovery and inventory work is finished, not just started. These ticks are not implementation stages.
A3: One row per site + team. Example: Site A / Planning. Leave a module as Not started until you have spoken to that group. Do not mark Done from memory of 'we think we covered it'.
A4: Row | B4: Site / location | C4: Team / function | D4: M1 Produced | E4: M2 Systems | F4: M3 How used | G4: M4 People | H4: M5 Pains | I4: M6 Needs | J4: Who we spoke to | K4: Date | L4: Notes
A5: Leave blank - for your count. | B5: Plant, region, or 'central'. | C5: Lead with CI managers, CI subject matter experts, and Digital. Add planning, finance, turnaround, commercial, or logistics only when that team produces or uses CI knowledge. | D5: Dropdown. | E5: Dropdown. | F5: Dropdown. | G5: Dropdown. | H5: Dropdown. | I5: Dropdown. | J5: Roles or names. | K5: Last session date. | L5: Anything missing.
A6: Example - delete | B6: Site A | C6: Planning | D6: Done | E6: In progress | F6: Not started | G6: Not started | H6: Not started | I6: Not started | J6: Planning manager, LP planner | K6: 2026-08-12 | L6: M1 session booked next week for operations

Sheet M1 Produced
A1: M1 - What CI already produces
A2: List every output the CI portfolio produces. One row per output. List first, then fill the reuse and quality columns. This list feeds every other sheet and the source inventory in the gap assessment.
A3: At the start, with the people who produce the outputs. Open Glossary and use the CI checklist first. Adjacent items (shift logs, commercial files, logistics claims) stay off this list unless they are used as CI knowledge.
A4: Example row? | B4: Item ID | C4: Name | D4: What it is (plain words) | E4: Which activity produces it | F4: Who produces it | G4: How often | H4: Made in (tool) | I4: Format | J4: Where it is stored | K4: Who owns it today | L4: Is it complete? | M4: Can we trust it to reuse? | N4: How easy to find | O4: Notes | P4: Knowledge type | Q4: Domain | R4: Structure | S4: Relevance to CI reuse | T4: Validity | U4: Quality tier today | V4: Uses Profisee terms today? | W4: Who approves it today | X4: Review cycle today
A5: Yes = example. Change to No when it is a real item, or delete the row. | B5: P-01, P-02… Must be unique. M3 and M6 will point here. | C5: The everyday name. Example: Monthly margin bridge. | D5: One or two sentences: what is in it, what question it answers. | E5: The meeting or routine that creates it. Example: monthly close, lookback review. | F5: Role or team. A named person helps. | G5: How often it is produced. | H5: Excel, PowerPoint, SAP, inbox, paper logbook… | I5: The form it is in. | J5: The real place: folder path, SharePoint library, mailbox, cabinet, laptop. | K5: Named person. If nobody owns it, write 'no clear owner'. | L5: Is the content up to date and filled in? | M5: Separate from complete: how much should the next person trust it? | N5: Could a new joiner find last year's copy without asking? | O5: Duplicates, sensitive content, known gaps. | P5: lesson learned, decision rationale, recommendation, best practice, expert judgment, or report | Q5: the CI area (lookback, Integrated Backcasting, post-audit, recurring CI report, decision review) | R5: structured, unstructured, or mixed | S5: high / medium / low | T5: still true / dated / unknown | U5: authoritative | reviewed | approved | indicative | supporting | V5: yes / no / unknown. Profisee is COMPANY's master-data taxonomy. | W5: role, or none | X5: monthly / quarterly / none / unknown
A6: Yes | B6: P-01 | C6: Decision lookback matrix | D6: List of past key decisions, what was decided, and what happened. Used to review decision quality over time. | E6: CI lookback reviews | F6: CI team | G6: Quarterly | H6: Excel | I6: Excel | J6: Shared drive > CI > Lookbacks | K6: CI lead | L6: Complete and current | M6: Reviewed - use with care | N6: Possible with effort | O6: EXAMPLE - replace or delete
A7: Yes | B7: P-02 | C7: Monthly margin bridge | D7: Spreadsheet that explains the gap between planned margin and actual margin, driver by driver (price, yield, timing, hedges). | E7: Monthly financial close | F7: Site controller | G7: Monthly | H7: Excel + ERP | I7: Excel | J7: Shared drive > Finance > Monthly close | K7: Site controller | L7: Complete and current | M7: Approved - safe to reuse | N7: Easy - anyone can find it | O7: EXAMPLE - the numbers are solid; the 'why' lives in emails
A8: Yes | B8: P-03 | C8: Refinery backcast report | D8: Compares actual performance with the best we could have done under the same conditions. Includes findings and recommendations. | E8: Backcasting cycle | F8: CI team + site economist | G8: Quarterly | H8: PowerPoint + planning model | I8: PowerPoint | J8: SharePoint > Backcasting | K8: CI lead | L8: Varies by site | M8: Reviewed - use with care | N8: Possible with effort | O8: EXAMPLE - recommendations tracked informally
A9: Yes | B9: P-04 | C9: Turnaround post-audit | D9: After a turnaround (a planned shutdown to maintain or upgrade units): what went to plan, what did not, what to do next time. | E9: Post-turnaround review | F9: Turnaround manager | G9: Every event | H9: Word + photos | I9: Word | J9: Project folder (varies by event) | K9: Turnaround manager | L9: Partly complete | M9: As captured - indicative only | N9: Hard | O9: EXAMPLE - past audits are hard to find before the next event
A10: Yes | B10: P-05 | C10: Shift logbook entries | D10: Notes on events, deviations, and decisions during each shift. | E10: Daily operations | F10: Shift operators | G10: Daily | H10: Logbook or paper | I10: Paper / handwritten | J10: Control room + scanned copies | K10: Operations supervisor | L10: Varies by site | M10: Raw notes - not reusable yet | N10: Hard | O10: EXAMPLE - rich context, mostly unstructured
A11: Yes | B11: P-06 | C11: Meeting minutes and decision emails | D11: Minutes of planning meetings plus email threads where options and trade-offs were discussed. | E11: Planning and S&OP meetings | F11: Meeting secretary / various | G11: Weekly | H11: Outlook / Word | I11: Email | J11: Individual mailboxes | K11: no clear owner | L11: Partly complete | M11: Raw notes - not reusable yet | N11: Only the producer can find it | O11: EXAMPLE - this is usually where the reasoning lives
A12: No | B12: P-07
A13: No | B13: P-08
A14: No | B14: P-09
A15: No | B15: P-10
A16: No | B16: P-11
A17: No | B17: P-12
A18: No | B18: P-13
A19: No | B19: P-14
A20: No | B20: P-15
A21: No | B21: P-16
A22: No | B22: P-17
A23: No | B23: P-18
... A80: No | B80: P-75

Sheet M2 Systems
A1: M2 - Where things live (systems and folders)
A2: One row per system or major storage place. 'Searchable' means: can a normal user find a specific past item in a few minutes?
A3: When: alongside M1, with Digital plus one user per system. IDs must be S-01, S-02… In 'What knowledge it holds', list M1 IDs (P-01) where you can.
A4: Example row? | B4: System ID | C4: System or storage place | D4: What it is used for day to day | E4: What knowledge lives here (use P- IDs) | F4: Form of what is stored | G4: Who can open it | H4: How searchable | I4: How long it is kept | J4: Known issues | K4: Notes
A5: Yes = example. Change to No for a real row. | B5: S-01, S-02… Unique. | C5: Planning model, SAP, SharePoint, shared drive, historian, logbook, Outlook… | D5: Example: runs the monthly plan; stores CI reports; shift records. | E5: Which M1 items or types sit here. | F5: Tables, documents, spreadsheets, email/notes, or mixed. | G5: Roles with access. Note if only two people can get in. | H5: Can a normal user find last year's item quickly? | I5: Example: 7 years; until the disk fills; no rule. | J5: Duplicates, version confusion, vendor lock, access bottleneck. | K5: Replacement plans, quirks.
A6: Yes | B6: S-01 | C6: Planning (LP) model environment | D6: Runs the monthly or weekly optimization plan. Holds model versions and yield vectors (the numbers that tell the model how units behave). | E6: LP model files, yield vectors, scenario assumptions | F6: Tables and fields (structured) | G6: Planning team only (2-3 people) | H6: Poor - browse folders by hand | I6: Model versions kept forever; assumptions not versioned | J6: Only the LP custodian really knows the model; vectors refreshed rarely | K6: EXAMPLE
A7: Yes | B7: S-02 | C7: Shared drive (G:) | D7: General file storage for CI, finance, and projects. | E7: P-01, P-02, P-04 and most CI reports | F7: Documents | G7: All staff | H7: Partly - you need to know where to look | I7: No rule | J7: Folder structures differ by team; duplicates are common | K7: EXAMPLE
A8: Yes | B8: S-03 | C8: Outlook mailboxes | D8: Day-to-day mail. Options, trade-offs, and quick decisions get discussed here. | E8: P-06 | F8: Unstructured text (email, notes) | G8: Individual owners only | H8: Poor - browse folders by hand | I8: Mailbox quota; leavers' mail is archived | J8: The reasoning behind decisions lives here and leaves when people leave | K8: EXAMPLE
A9: No | B9: S-04
A10: No | B10: S-05
A11: No | B11: S-06
A12: No | B12: S-07
A13: No | B13: S-08
A14: No | B14: S-09
A15: No | B15: S-10
A16: No | B16: S-11
A17: No | B17: S-12
A18: No | B18: S-13
A19: No | B19: S-14
A20: No | B20: S-15
... A40: No | B40: S-35

Sheet M3 How used
A1: M3 - How each output is used
A2: For each item from M1: who uses it, what they take from it, and whether anything actually changes. Honest 'filed, nothing further' is useful.
A3: When: after M1, with the people who USE the outputs (often not the producers). Type a P- ID in column B. Column C fills in the name from M1 automatically. The four closures are the ways a finding is supposed to land: planning model, procedure, next plan, or a person's know-how written down. We are recording whether a finding lands today. This phase does not build the process that makes a finding change the next plan or model.
A4: Example row? | B4: Item ID (from M1) | C4: Name (from M1 - do not type) | D4: Who uses it | E4: What they use it for | F4: Which process step it feeds | G4: What they actually take from it | H4: What happens next | I4: Is follow-up checked? | J4: Which closure (if any) | K4: What is hard to reconstruct later | L4: What would make this more useful
A5: Yes = example. | B5: Must match an Item ID on M1 Produced (P-01…). Pick from the dropdown if it appears. | C5: Filled by formula from M1. If this is blank, the ID is missing or mistyped. | D5: Roles that actually read or apply it. | E5: The decision or task it feeds. | F5: Monthly planning, S&OP, budget, next turnaround, next backcast… | G5: The number, lesson, or recommendation that gets used - vs ignored. | H5: Does a plan, model, or procedure change, or is it filed? | I5: Is anyone checking the change actually happened? | J5: The four intended landings. Pick None if it does not land anywhere. | K5: In 6-12 months, what context would be missing: why, assumptions, alternatives, who was in the room. | L5: Better format, earlier timing, more context, easier to find…
A6: Yes | B6: P-02 | C6: =IF(B6="","",IFERROR(INDEX('M1 Produced'!C:C,MATCH(B6,'M1 Produced'!B:B,0)),"ID not found on M1")) | D6: Planners, finance, CI team | E6: Understand why actual margin differed from plan. Feeds commentary in the CI report. | F6: Monthly CI reporting; planning review | G6: The variance numbers and the commentary | H6: Informs a decision (informal) | I6: No | J6: None of these | K6: Why certain operational calls were made during the month - not in the bridge | L6: Link each variance driver to the decision that caused it
A7: Yes | B7: P-03 | C7: =IF(B7="","",IFERROR(INDEX('M1 Produced'!C:C,MATCH(B7,'M1 Produced'!B:B,0)),"ID not found on M1")) | D7: CI team, site economist, planning manager | E7: Find improvement opportunities. Some should feed LP model updates. | F7: Annual planning model refresh | G7: The recommendations list | H7: Changes a plan or model | I7: Assigned but not checked | J7: Finding updates the planning model | K7: The assumptions behind the backcast - hard to re-run later | L7: Record assumptions with the report; named owner per recommendation
A8: Yes | B8: P-04 | C8: =IF(B8="","",IFERROR(INDEX('M1 Produced'!C:C,MATCH(B8,'M1 Produced'!B:B,0)),"ID not found on M1")) | D8: Next turnaround team (5-7 years later) | E8: Avoid repeating mistakes; help scope the next turnaround. | F8: Next turnaround planning | G8: The lessons section | H8: Filed - nothing further | I8: No | J8: None of these | K8: Everything - even finding the last audit is hard | L8: One storage place; a searchable lessons list
A9: No | C9: =IF(B9="","",IFERROR(INDEX('M1 Produced'!C:C,MATCH(B9,'M1 Produced'!B:B,0)),"ID not found on M1"))
A10: No | C10: =IF(B10="","",IFERROR(INDEX('M1 Produced'!C:C,MATCH(B10,'M1 Produced'!B:B,0)),"ID not found on M1"))
A11: No | C11: =IF(B11="","",IFERROR(INDEX('M1 Produced'!C:C,MATCH(B11,'M1 Produced'!B:B,0)),"ID not found on M1"))
A12: No | C12: =IF(B12="","",IFERROR(INDEX('M1 Produced'!C:C,MATCH(B12,'M1 Produced'!B:B,0)),"ID not found on M1"))
A13: No | C13: =IF(B13="","",IFERROR(INDEX('M1 Produced'!C:C,MATCH(B13,'M1 Produced'!B:B,0)),"ID not found on M1"))
A14: No | C14: =IF(B14="","",IFERROR(INDEX('M1 Produced'!C:C,MATCH(B14,'M1 Produced'!B:B,0)),"ID not found on M1"))
A15: No | C15: =IF(B15="","",IFERROR(INDEX('M1 Produced'!C:C,MATCH(B15,'M1 Produced'!B:B,0)),"ID not found on M1"))
A16: No | C16: =IF(B16="","",IFERROR(INDEX('M1 Produced'!C:C,MATCH(B16,'M1 Produced'!B:B,0)),"ID not found on M1"))
A17: No | C17: =IF(B17="","",IFERROR(INDEX('M1 Produced'!C:C,MATCH(B17,'M1 Produced'!B:B,0)),"ID not found on M1"))
A18: No | C18: =IF(B18="","",IFERROR(INDEX('M1 Produced'!C:C,MATCH(B18,'M1 Produced'!B:B,0)),"ID not found on M1"))
A19: No | C19: =IF(B19="","",IFERROR(INDEX('M1 Produced'!C:C,MATCH(B19,'M1 Produced'!B:B,0)),"ID not found on M1"))
A20: No | C20: =IF(B20="","",IFERROR(INDEX('M1 Produced'!C:C,MATCH(B20,'M1 Produced'!B:B,0)),"ID not found on M1"))
... A60: No | C60: =IF(B60="","",IFERROR(INDEX('M1 Produced'!C:C,MATCH(B60,'M1 Produced'!B:B,0)),"ID not found on M1"))

Sheet M4 People
A1: M4 - People and know-how (what is not written down)
A2: Critical knowledge that lives in people's heads: judgment, workarounds, 'if you see this, do that'. This is normal. The risk is having no backup.
A3: When: short interviews with CI managers and experienced CI staff. Roles are fine if you do not want names. Split 'how big is the risk' from 'why' and 'when they could leave' - those are three different facts. IDs must be K-01, K-02…
A4: Example row? | B4: Person ID | C4: Person or role | D4: Area of expertise | E4: What they know that is not written down | F4: Where it shows up (which decisions) | G4: Who else has this knowledge | H4: How big is the risk | I4: Why it is at risk | J4: When they could leave or rotate | K4: Has any of it been captured? | L4: Priority to capture | M4: Notes
A5: Yes = example. | B5: K-01, K-02… Unique. | C5: Name or just the role. Example: Senior LP planner, Site A. | D5: What they are the go-to person for. | E5: Judgment calls, shortcuts, 'if you see X, do Y'. | F5: Crude selection, scheduling, pricing, troubleshooting… | G5: Backup person. 'Nobody' is an important answer. | H5: High / Medium / Low - size of the hole if they leave tomorrow. | I5: The reason: only one person, retirement, rotation, contractor. | J5: Best estimate: retires ~2028, rotates every 2-3 years, contract ends Q4. | K5: No / partly / written / written and findable. | L5: High / Medium / Low for capture work. | M5: Good candidate for a recorded interview or shadowing?
A6: Yes | B6: K-01 | C6: Senior LP planner (Site A) | D6: LP model behavior, crude valuation | E6: Knows which model quirks to distrust and when. Keeps informal notes on past model errors. | F6: Monthly plan sign-off; crude slate decisions | G6: Nobody - single holder | H6: High | I6: Single holder - no backup | J6: ~2028 (retirement) | K6: Partly | L6: High | M6: EXAMPLE - first interview candidate
A7: Yes | B7: K-02 | C7: Turnaround manager | D7: Turnaround scoping and execution | E7: Remembers what went wrong in 2019 and 2023. Knows which contractors under-deliver. | F7: Turnaround planning every 5-7 years | G7: Deputy (partly) | H7: Medium | I7: Regular rotation | J7: Rotates about every 3 years | K7: No | L7: High | M7: EXAMPLE
A8: No | B8: K-03
A9: No | B9: K-04
A10: No | B10: K-05
A11: No | B11: K-06
A12: No | B12: K-07
A13: No | B13: K-08
A14: No | B14: K-09
A15: No | B15: K-10
A16: No | B16: K-11
A17: No | B17: K-12
A18: No | B18: K-13
A19: No | B19: K-14
... A40: No | B40: K-35

Sheet M5 Pains
A1: M5 - Pain points (where it hurts today)
A2: Write it as you would tell a colleague. Stories and rough numbers both count. These rows become the case for change and the evidence behind M6 needs.
A3: A mixed CI group. Not the whole value chain. Capture every example people raise. A typical-pain tag is optional. IDs must still be unique (PP-01, PP-02...).
A4: Example row? | B4: Pain ID | C4: What goes wrong (plain words) | D4: Type of pain | E4: Typical pain (if it fits) | F4: Where it happens | G4: How often | H4: What it costs (rough is fine) | I4: A real example or story | J4: Raised by | K4: Notes
A5: Yes = example. | B5: PP-01, PP-02… Unique. M6 points here. | C5: The situation in one or two sentences. | D5: Pick the closest type. | E5: Optional. Use Typical pains if a row fits. Pick Other if it does not. | F5: Process, team, or site. | G5: How often it shows up. | H5: Time, money, rework, delay. Example: ~2 days of rework a month. | I5: What happened, when, impact. This is what makes the row believable. | J5: Role is enough. | K5: Anything else.
A6: Yes | B6: PP-01 | C6: Before the last turnaround, nobody could locate the previous post-audit. The team started from scratch. | D6: Can't find what we need | E6: 1 - Can't find things / context lost | F6: Turnarounds | G6: Rare but serious | H6: Weeks of rework; same avoidable issues came back | I6: 2024 turnaround planning - prior lessons found after the fact in an old project folder | J6: Turnaround team | K6: EXAMPLE
A7: Yes | B7: PP-02 | C7: The planner who ran crude valuation left. Her replacement rebuilt the approach and repeated an error she had already flagged in an email. | D7: Knowledge left with a person | E7: 7 - Knowledge walks out with people | F7: Crude planning | G7: A few times a year | H7: ~2-4 weeks of rework; one repeated valuation error | I7: 2025 rotation - handover notes did not cover the judgment calls | J7: Planning manager | K7: EXAMPLE
A8: Yes | B8: PP-03 | C8: Lookback findings are presented at the CI review but there is no tracked route into the planning model. The same model errors are rediscovered later. | D8: Same problem keeps coming back | E8: 3 - Findings never reach the plan or model | F8: CI to planning handoff | G8: About monthly | H8: Model runs on stale assumptions; same variances re-explained each cycle | I8: Same yield assumption flagged in three consecutive quarterly backcasts | J8: CI analyst | K8: EXAMPLE
A9: No | B9: PP-04
A10: No | B10: PP-05
A11: No | B11: PP-06
A12: No | B12: PP-07
A13: No | B13: PP-08
A14: No | B14: PP-09
A15: No | B15: PP-10
A16: No | B16: PP-11
A17: No | B17: PP-12
A18: No | B18: PP-13
A19: No | B19: PP-14
A20: No | B20: PP-15
... A50: No | B50: PP-45

Sheet M6 Needs
A1: M6 - What the CI KM framework must support
A2: Write needs as outcomes, not tools. Bad: buy a portal. Good: anyone can find the last lookback in under a minute. Every need must point at a pain or an asset. These rows feed the reconciled requirements list. They are not a build backlog for this SOW.
A3: When: last, once M1-M5 have evidence. Sponsor plus the people who ran the earlier modules. When it would matter means This SOW / later phase / later, with AI. This is not workbook fill order, and it is not a build schedule for this engagement. IDs must be N-01, N-02…
A4: Example row? | B4: Need ID | C4: What we need (outcome, plain words) | D4: Why - point at evidence (PP-, P-, K- IDs) | E4: Typical pain it would ease (if it fits) | F4: Who benefits | G4: What 'good' looks like | H4: Priority | I4: When it would matter | J4: Which closure it supports | K4: Agreed by | L4: Status | M4: Notes
A5: Yes = example. | B5: N-01, N-02… Unique. | C5: One sentence describing the result. | D5: Must cite at least one ID from M5, M1, or M4. If you cannot, question the need. | E5: Optional. Use Typical pains if a need would ease one. Pick Other if it does not. | F5: Roles or teams who would use or gain. | G5: A test you could run. Example: a new planner finds prior learning without asking anyone. | H5: Must / Should / Could / Not now. | I5: This SOW / later phase / later, with AI. This is not workbook fill order, and it is not a build schedule for this engagement. | J5: If this need is about landing a finding somewhere, pick which landing. | K5: Who signed this off. | L5: Draft / Agreed / Parked for later phase / Done. | M5: Anything else.
A6: Yes | B6: N-01 | C6: A single, searchable place for all lookback, backcast, and post-audit outputs, with a named owner for each item. | D6: PP-01; P-01 through P-06 are scattered across drives, SharePoint, and mailboxes | E6: 1 - Can't find things / context lost | F6: Everyone producing or using CI outputs | G6: Any user finds a past review in under a minute, by site, topic, or decision type | H6: Must have | I6: This SOW | J6: None of these | L6: Draft | M6: EXAMPLE
A7: Yes | B7: N-02 | C7: A standard record for lessons and decisions that captures the why (assumptions, alternatives, constraints) next to the what. | D7: PP-02, PP-03; M3 column 'what is hard to reconstruct later' | E7: 2 - Reviews report numbers, not lessons | F7: CI team, planners, turnaround teams | G7: A reviewer can understand a decision without asking the author | H7: Must have | I7: This SOW | J7: Person's know-how is written into the system | L7: Draft | M7: EXAMPLE
A8: Yes | B8: N-03 | C8: A tracked route from findings into the planning model, procedures, and next-cycle plans, with proof the change happened. | D8: PP-03; M3 'what happens next' | E8: 3 - Findings never reach the plan or model | F8: Planning, CI team, site leadership | G8: Every accepted recommendation has an owner, a due date, and evidence of closure | H8: Should have | I8: later phase | J8: Finding updates the planning model | L8: Draft | M8: EXAMPLE
A9: Yes | B9: N-04 | C9: Capture of critical know-how from the highest-risk people before they rotate or retire. | D9: K-01, K-02 | E9: 7 - Knowledge walks out with people | F9: Planning, operations, turnaround teams | G9: Top 10 high-risk holders have their key judgment written down and findable | H9: Must have | I9: This SOW | J9: Person's know-how is written into the system | L9: Draft | M9: EXAMPLE
A10: No | B10: N-05
A11: No | B11: N-06
A12: No | B12: N-07
A13: No | B13: N-08
A14: No | B14: N-09
A15: No | B15: N-10
A16: No | B16: N-11
A17: No | B17: N-12
A18: No | B18: N-13
A19: No | B19: N-14
A20: No | B20: N-15
A21: No | B21: N-16
... A50: No | B50: N-45

Sheet Glossary
A1: Glossary - words used in this workbook
A2: Every term used in a column header is here in plain words.
A3: If a word on another sheet is unclear, come here first. The checklist at the bottom is for M1 - tick what exists, add anything missing.
A4: Term | B4: Plain meaning
A5: CI (continuous improvement) | B5: The ongoing work of reviewing performance and finding better ways: lookbacks, backcasts, audits, improvement projects.
A6: Lookback | B6: A review of what actually happened vs what was planned. Example: a monthly review of why actual margin differed from the plan.
A7: Backcast (operational) | B7: Given what actually happened (prices, demand, equipment), what was the BEST we could have done - and how close did we get?
A8: Backcast (strategic) | B8: A long-term plan that starts from a desired future and works backward to today's choices. Same word, different exercise. Do not mix them in one row.
A9: Post-audit | B9: A review after a project or event (like a turnaround) to capture what went well and what to do differently next time.
A10: Turnaround | B10: A planned shutdown of a unit or site to inspect, maintain, or upgrade it. Often years apart, so lessons are easy to lose.
A11: LP (linear program) | B11: The planning model that picks the economically best plan under constraints. Often called PIMS, RPMS, or 'the planning model'.
A12: Yield vector | B12: A set of numbers in the LP that describe how a unit turns feed into products. If it is stale, the plan is stale.
A13: Knowledge asset | B13: Anything worth keeping and reusing: a report, a lesson, a decision record, a person's expertise.
A14: Output / item (M1) | B14: Any document or record the work produces: report, deck, spreadsheet, matrix, minutes, logbook, email thread, recording.
A15: System (M2) | B15: The place something lives: SharePoint, drive, planning tool, mailbox, cabinet.
... A36: This SOW | B36: the design-and-foundation engagement. It specifies the framework, governance, technology direction, and a roadmap for later phases. It does not implement a platform.
A37: Checklist for M1 - typical items to look for
A38: Tick what exists. Add anything missing. Starred items are ones CI practice usually already produces.
A39: Typical item
A40: * Decision lookback matrix
A41: * Decision-point maturity assessments | B41: CI assessments of how well key decision points are managed
A42: * Operational lookback reports / decks | B42: Regular operational reviews (monthly / quarterly)
A43: * Integrated Backcasting / refinery backcast reports | B43: Integrated Backcasting / backcasting cycles comparing actual vs best possible
A44: * Regional backcasting outputs | B44: Regional or strategic backcasting
A45: * Post-audit reports (projects, turnarounds) | B45: Post-project and post-turnaround reviews
A46: * Recurring CI reports | B46: Regular CI reporting to management
A47: Governance outputs (modes, decisions, actions) | B47: CI governance meetings
A48: Monthly margin bridge / variance analysis | B48: Monthly financial close (controller)
A49: Yield reconciliation | B49: Monthly close - actual vs planned volumes
A50: Planning model files and versions (LP) | B50: Planning team
A51: KPI definition sheets | B51: Whoever maintains performance metrics
A52: S&OP / planning meeting minutes | B52: Planning and S&OP meetings
... A60: * SME know-how (unwritten) | B60: Experienced planners, operators, turnaround managers - capture on M4

Sheet Typical pains
A1: Typical pains (optional tags)
A2: These are common places knowledge work hurts. Use them as optional tags on M5 (pains) and M6 (needs). You do not have to force a story into one of these. If it does not fit, pick Other or leave blank.
A3: These tags help group stories. They are not a promise that this SOW will close each one. You do not have to tag every row. Item 4 (assumptions) and item 5 (KPI names) are easy to miss. If a story sounds like that, glance at those two.
A4: Typical pain | B4: In one sentence | C4: What a row on this workbook should show
A5: 1 - Can't find things / context lost | B5: Reports and the 'why' sit in drives, mailboxes, and logbooks. The rationale evaporates. | C5: M1 rows with Hard / Only the producer can find it. M2 searchability = Poor.
A6: 2 - Reviews report numbers, not lessons | B6: Variance is measured. Causes, assumptions, and reusable guidance are not. | C6: M3: filed, nothing further. M1 trust to reuse = raw or indicative.
A7: 3 - Findings never reach the plan or model | B7: A lookback finds a problem. The LP or next plan does not change. The same variance comes back. | C7: M3 follow-up = No or assigned but not checked. Closure = None.
A8: 4 - Assumptions and uncertainty not recorded | B8: Price and yield assumptions are not versioned against the decision they informed. Later you cannot tell bad luck from a bad call. | C8: M3 'hard to reconstruct' mentions assumptions. M1 has no assumption log.
A9: 5 - KPIs and names don't match | B9: The same metric or stream has different names or bases across teams, so lessons do not compare. | C9: M1 missing KPI definition sheet. M5 story about talking past each other on numbers.
A10: 6 - Root cause is weak or missing | B10: Reviews stop at 'price' or 'yield' without a real cause, so the fix is guesswork. | C10: M5 type = same problem keeps coming back, with no RCA output on M1.
A11: 7 - Knowledge walks out with people | B11: Judgment sits with one person. Rotation, retirement, or a contractor ending takes it with them. | C11: M4 High risk, nobody else has it, capture = No.
A12: 8 - Backcasting is thin or unused | B12: Best-possible vs actual is skipped, informal, or not used to change the next plan. | C12: No backcast row on M1, or M3 says the backcast is filed.
A14: The four closures. A finding is not done until one of these is true and checked.
A15: 1. Finding updates the planning model. 2. Lesson becomes a procedure or standard. 3. Finding updates the next plan or pathway. 4. A person's know-how is written into the system. M3 asks which one happened. M6 asks which one a need is meant to support.

Sheet _Lists
A1: A | B1: B | C1: C | D1: D | E1: E | F1: F | G1: G | H1: H | I1: I | J1: J | K1: K | L1: L | M1: M | N1: N | O1: O | P1: P | Q1: Q | R1: R | S1: S | T1: Typical pain | U1: U | V1: Source pack | W1: Alignment | X1: Knowledge type | Y1: Structure | Z1: Relevance | AA1: Validity | AB1: Quality tier | AC1: Profisee | AD1: Review cycle
A2: Yes | B2: Every event | C2: Excel | D2: Complete and current | E2: Easy - anyone can find it | F2: Approved - safe to reuse | G2: Tables and fields (structured) | H2: Easy - search works | I2: Changes a plan or model | J2: Yes - assigned and checked done | K2: Finding updates the planning model | L2: High | M2: Single holder - no backup | N2: No | O2: Same problem keeps coming back | P2: Constantly | Q2: Must have | R2: This SOW | S2: Draft | T2: 1 - Can't find things / context lost | U2: Not started | V2: VCO KM Functional Requirements | W2: Aligned | X2: lesson learned | Y2: structured | Z2: high | AA2: still true | AB2: authoritative | AC2: yes | AD2: monthly
A3: No | B3: Daily | C3: PowerPoint | D3: Partly complete | E3: Possible with effort | F3: Reviewed - use with care | G3: Documents | H3: Partly - you need to know where to look | I3: Changes a procedure or standard | J3: Assigned but not checked | K3: Lesson becomes a procedure or standard | L3: Medium | M3: Retirement coming | N3: Partly | O3: Knowledge left with a person | P3: About monthly | Q3: Should have | R3: later phase | S3: Agreed | T3: 2 - Reviews report numbers, not lessons | U3: In progress | V3: AI-enabled KM (Integrated Backcasting) | W3: Unique | X3: decision rationale | Y3: unstructured | Z3: medium | AA3: dated | AB3: reviewed | AC3: no | AD3: quarterly
B4: Weekly | C4: Word | D4: Outdated | E4: Hard | F4: As captured - indicative only | G4: Spreadsheets | H4: Poor - browse folders by hand | I4: Informs a decision (informal) | J4: No | K4: Finding updates the next plan or pathway | L4: Low | M4: Regular rotation | N4: Yes - written down | O4: Decision made without past learning | P4: A few times a year | Q4: Could have | R4: later, with AI | S4: Parked for later phase | T4: 3 - Findings never reach the plan or model | U4: Done | V4: Both | W4: Conflict | X4: recommendation | Y4: mixed | Z4: low | AA4: unknown | AB4: approved | AC4: unknown | AD4: none
B5: Monthly | C5: PDF | D5: Varies by site | E5: Only the producer can find it | F5: Raw notes - not reusable yet | G5: Unstructured text (email, notes) | I5: Filed - nothing further | K5: Person's know-how is written into the system | M5: Contractor / external | N5: Yes - written down and findable | O5: Can't find what we need | P5: Rare but serious | Q5: Not now | S5: Done | T5: 4 - Assumptions and uncertainty not recorded | V5: Added in discovery | W5: Gap | X5: best practice | AB5: indicative | AD5: unknown
B6: Quarterly | C6: Email | D6: Don't know | F6: Don't know | G6: Mixed | I6: Don't know | K6: None of these | M6: Other | O6: Context lost over time | T6: 5 - KPIs and names don't match | W6: Needs COMPANY decision | X6: expert judgment | AB6: supporting
B7: Annually | C7: System record | O7: Other | T7: 6 - Root cause is weak or missing | X7: report
B8: Every few years | C8: Paper / handwritten | T8: 7 - Knowledge walks out with people
B9: As needed | C9: Recording | T9: 8 - Backcasting is thin or unused
C10: Other | T10: Other / not sure
